{
  "recentFiles": [
    {
      "basename": "202410171217 Drifting away....",
      "path": "02 - Areas/01 - Mini Essays/202410171217 Drifting away.....md"
    },
    {
      "basename": "Ethics and Values Notes",
      "path": "Ethics and Values Notes.md"
    },
    {
      "basename": "00 - C++ Projects",
      "path": "01 - Projects/02 - C++ Projects/00 - C++ Projects.md"
    },
    {
      "basename": "01 Bookshop Management System",
      "path": "01 - Projects/02 - C++ Projects/01 Bookshop Management System.md"
    },
    {
      "basename": "20241013",
      "path": "06 - Daily/01 - Daily/20241013.md"
    },
    {
      "basename": "logMessage",
      "path": "TagsRoutes/logMessage.md"
    },
    {
      "basename": "Focus",
      "path": "Focus.md"
    },
    {
      "basename": "202408281424 How to Enhance Focus and Improve Productivity",
      "path": "02 - Areas/02 - Podcasts/202408281424 How to Enhance Focus and Improve Productivity.md"
    },
    {
      "basename": "20241012",
      "path": "06 - Daily/01 - Daily/20241012.md"
    },
    {
      "basename": "(TEMPLATE) Daily",
      "path": "99 - Meta/00 - Templates/(TEMPLATE) Daily.md"
    },
    {
      "basename": "(TEMPLATE) Daily (Vanilla)",
      "path": "99 - Meta/00 - Templates/(TEMPLATE) Daily (Vanilla).md"
    },
    {
      "basename": "(TEMPLATE) Trial",
      "path": "99 - Meta/00 - Templates/(TEMPLATE) Trial.md"
    },
    {
      "basename": "(TEMPLATE) Weekly",
      "path": "99 - Meta/00 - Templates/(TEMPLATE) Weekly.md"
    },
    {
      "basename": "Probability and statistics",
      "path": "Probability and statistics.md"
    },
    {
      "basename": "W40 e-matrix",
      "path": "06 - Daily/02 - Weekly/W40 e-matrix.md"
    },
    {
      "basename": "W37 e-matrix",
      "path": "06 - Daily/02 - Weekly/W37 e-matrix.md"
    },
    {
      "basename": "202408240501 About Writing",
      "path": "02 - Areas/01 - Mini Essays/202408240501 About Writing.md"
    }
  ],
  "omittedPaths": [],
  "maxLength": null,
  "openType": "tab"
}